ewhs/__init__.py
ewhs/client.py
ewhs/exceptions.py
ewhs/mixins.py
ewhs/resources.py
ewhs_api_python-1.2.0.dist-info/LICENSE
ewhs_api_python-1.2.0.dist-info/METADATA
ewhs_api_python-1.2.0.dist-info/WHEEL
ewhs_api_python-1.2.0.dist-info/RECORD
