Metadata-Version: 2.1
Name: ewhs-api-python
Version: 1.2.0
Summary: Python library for the eWarehousing Solutions API.
Author: Liam Boer
Author-email: liam.boer@notive.nl
Requires-Python: >=3.7,<4.0
Classifier: Programming Language :: Python :: 3
Classifier: Programming Language :: Python :: 3.7
Classifier: Programming Language :: Python :: 3.8
Classifier: Programming Language :: Python :: 3.9
Classifier: Programming Language :: Python :: 3.10
Classifier: Programming Language :: Python :: 3.11
Requires-Dist: requests (>=2.26.0,<3.0.0)
